{
    "author": "Gmase",
    "build": "00007",
    "context": "client",
    "date": "2017-03-29",
    "description": "MMO Galactic War Canis Major Dwarf",
    "display_name": "Multiplayer Galactic War CMD",
    "forum": "https://forums.uberent.com/threads/rel-canis-major-dwarf-beta.72310/",
    "identifier": "com.gmase.cmd",
    "version": "7",
	"signature": " ",
    "scenes": {
        "start": [
            "coui://ui/mods/com.gmase.cmd/start.js"
        ]
    },
    "unitList": false,
    "fileSystem": false,
    "searchable": [
        "gmase",
        "cmd",
        "metagame"
    ],
    "sort": "cmd",
    "authors": [
        "gmase"
    ],
    "icon": "http://i.imgur.com/Cx9Xsac.png",
    "priority": 50,
    "dependencies": ["info.nanodesu.pastats"],
    "companions": [],
    "framework": false,
    "available": true,
    "enabled": true,
    "titansOnly": false,
    "classicOnly": false,
    "classic": false,
    "titans": false,
    "conflicts": {}
}